nibo/__init__.py
nibo/__version__.py
nibo/api.py
nibo/boletos.py
nibo/clientes.py
nibo-0.2.0.dist-info/licenses/LICENSE
nibo-0.2.0.dist-info/METADATA
nibo-0.2.0.dist-info/WHEEL
nibo-0.2.0.dist-info/top_level.txt
nibo-0.2.0.dist-info/RECORD
