Metadata-Version: 2.4
Name: Nibo
Version: 0.2.0
Summary: Extrai informações do Nibo
Author-email: Chen <chenpsilva@gmail.com>
License: MIT
Classifier: Programming Language :: Python :: 3
Classifier: License :: OSI Approved :: MIT License
Classifier: Operating System :: OS Independent
Requires-Python: >=3.10
License-File: LICENSE
Requires-Dist: pydantic>=2.10
Requires-Dist: python-dotenv>=1.1
Requires-Dist: requests>=2.32
Dynamic: license-file
